hqm/__init__.py
hqm/run_all.sh
hqm/check/part_reco/Bd2Kspsi2S_MC_highq2_check.py
hqm/check/part_reco/Jpsi_region.py
hqm/check/part_reco/check_psi2S_left_tail.py
hqm/check/part_reco/psi2S_region.py
hqm/check/part_reco/simultaneous_fit.py
hqm/data_sample/add_selection.py
hqm/data_sample/add_selection_script.sh
hqm/data_sample/apply_preselection.py
hqm/data_sample/job_sel
hqm/data_sample/submit_add_selection.sh
hqm/data_sample/submit_all_ee.sh
hqm/data_sample/submit_all_mm.sh
hqm/data_sample/submit_sel
hqm/data_sample/truth_match.py
hqm/model/KDE_shape.py
hqm/model/__init__.py
hqm/model/double_swap.py
hqm/model/part_reco.py
hqm/model/plot_rare_part_reco.py
hqm/model/rare_part_reco.py
hqm/model/signal.py
hqm/part_reco/convolution_shape.py
hqm/part_reco/fit_convolution.py
hqm/part_reco/run_convolution_shape.sh
hqm/part_reco/run_fit.sh
hqm/part_reco/mm_comb/comb_shape_mm.py
hqm/part_reco/mm_comb/run_mm.sh
hqm/part_reco/ratio/fit_MC.py
hqm/part_reco/ratio/fully_reco_shape.py
hqm/part_reco/ratio/run_fit_MC.sh
hqm/part_reco/ratio/run_fully_reco_shape.sh
hqm/part_reco/ratio/simultaneous_fit.py
hqm/part_reco/ratio/simultaneous_fit_script.sh
hqm/part_reco/ratio/submit_simultaneous_fit.sh
hqm/part_reco/systematic/sys1/convolution_shape_sys1.py
hqm/part_reco/systematic/sys1/fit_convolution_sys1.py
hqm/part_reco/systematic/sys1/run_convolution_shape_sys1.sh
hqm/part_reco/systematic/sys1/run_fit_sys1.sh
hqm/part_reco/systematic/sys1/submit_fit_sys1.sh
hqm/signal/fit_Bu2Kee_MC.py
hqm/signal/fit_Bu2Kmm_MC.py
hqm/signal/run_ee.sh
hqm/signal/run_mm.sh
hqm/signal/systematic/sys1/fit_Bu2Kee_MC_sys1.py
hqm/signal/systematic/sys1/fit_Bu2Kmm_MC_sys1.py
hqm/signal/systematic/sys1/run_ee_sys1.sh
hqm/signal/systematic/sys1/run_mm_sys1.sh
hqm/signal/systematic/sys1/submit_ee_sys1.sh
hqm/signal/systematic/sys1/submit_mm_sys1.sh
hqm/tools/Cut.py
hqm/tools/fit.py
hqm/tools/plot.py
hqm/tools/selection.py
hqm/tools/utility.py
hqm_data/KDE_2011_ETOS_high_bdks.json
rx_hqm-0.2.3.dist-info/METADATA
rx_hqm-0.2.3.dist-info/WHEEL
rx_hqm-0.2.3.dist-info/top_level.txt
rx_hqm-0.2.3.dist-info/RECORD
