Metadata-Version: 2.1
Name: rx_hqm
Version: 0.2.3
Requires-Dist: zfit
Requires-Dist: hist
Requires-Dist: mplhep
Requires-Dist: awkward
Requires-Dist: matplotlib
Requires-Dist: numpy
Requires-Dist: rx-tools
Requires-Dist: rx-monitor
Requires-Dist: rx-scripts
